pyqecc/__init__.py
pyqecc/channel/__init__.py
pyqecc/channel/abstruct.py
pyqecc/channel/channel.py
pyqecc/qecc/__init__.py
pyqecc/qecc/abstruct.py
pyqecc/qecc/bosonic.py
pyqecc/qecc/concatenated.py
pyqecc/qecc/stabilizer.py
pyqecc/qecc/topological.py
pyqecc/qecc/toy.py
pyqecc/sim/__init__.py
pyqecc/sim/bler.py
pyqecc/util/__init__.py
pyqecc/util/util.py
pyqecc/util/util_topological.py
pyqecc-0.0.2.dist-info/DESCRIPTION.rst
pyqecc-0.0.2.dist-info/METADATA
pyqecc-0.0.2.dist-info/RECORD
pyqecc-0.0.2.dist-info/WHEEL
pyqecc-0.0.2.dist-info/metadata.json
pyqecc-0.0.2.dist-info/top_level.txt
